<keymap version="1" name="IntelliJ (GNOME) copy 1" parent="Default for GNOME">
  <action id="FindInPath" />
  <action id="SearchEverywhere">
    <keyboard-shortcut first-keystroke="shift ctrl f" />
  </action>
  <action id="Debug">
    <keyboard-shortcut first-keystroke="f5" />
  </action>
  <action id="Run">
    <keyboard-shortcut first-keystroke="shift f5" />
  </action>
  <action id="EditorStartNewLineBefore" />
  <action id="QuickActionPopup" />
  <action id="RearrangeCode">
    <keyboard-shortcut first-keystroke="ctrl alt enter" />
  </action>
</keymap>
